{
    "homepage":  "https://github.com/liifi/workstation",
    "url":  "https://raw.githubusercontent.com/liifi/workstation/de9f14b/lib/scripts/liifi-scoop-basics.ps1",
    "bin":  [
                "liifi-scoop-basics.ps1"
            ],
    "depends":  [
                    "liifi-corpca",
                    "liifi-edit-bucket",
                    "liifi-edit-hosts",
                    "liifi-git-defaults",
                    "liifi-hyperv",
                    "liifi-myhome",
                    "liifi-prompt-basic",
                    "liifi-prompt-git",
                    "liifi-ssh-agent",
                    "liifi-ssh-git",
                    "liifi-ssh-id-add",
                    "liifi-ssh-id-create",
                    "liifi-ssh-server",
                    "liifi-tools-docker",
                    "liifi-tools-k8s",
                    "liifi-tools-pwsh",
                    "liifi-tools-rancher",
                    "liifi-vscode",
                    "liifi-wsl-k3s",
                    "liifi-wsl-ubuntu"
                ],
    "version":  "2019-12-08-10-57",
    "hash":  "F2170C7A959DB138A9B591EBD3F20BC302A831F3DFCB89DCE2B2B8550F7E1AFE"
}
